mqtty/__init__.py
mqtty/manager.py
mqtty/mqtt_connection.py
mqtty/mqtty.py
mqtty/py.typed
mqtty/types.py
ki2_mqtty-1.4.0.dist-info/LICENSE
ki2_mqtty-1.4.0.dist-info/METADATA
ki2_mqtty-1.4.0.dist-info/WHEEL
ki2_mqtty-1.4.0.dist-info/RECORD
