Metadata-Version: 2.1
Name: ki2-mqtty
Version: 1.4.0
Summary: mqtty is a flexible Python package that bridges MQTT communication with serial devices. It provides an agnostic approach to MQTT client libraries, supporting both paho-mqtt and aiomqtt through helper functions, while allowing developers to manage multiple serial devices seamlessly.
Home-page: https://gitlab.com/ki2-open/python/mqtty
License: MIT
Author: Adrien KERFOURN
Author-email: ak.sitecontact@gmail.com
Requires-Python: >=3.10,<4.0
Classifier: License :: OSI Approved :: MIT License
Classifier: Programming Language :: Python :: 3
Classifier: Programming Language :: Python :: 3.10
Classifier: Programming Language :: Python :: 3.11
Classifier: Programming Language :: Python :: 3.12
Classifier: Programming Language :: Python :: 3.13
Requires-Dist: ki2-python-utils (>=0.3.4,<0.4.0)
Requires-Dist: typing-extensions (>=4.12.2,<5.0.0)
Project-URL: Repository, https://gitlab.com/ki2-open/python/mqtty
